setup.py
filestats/__init__.py
filestats/filestats.py
filestats.egg-info/PKG-INFO
filestats.egg-info/SOURCES.txt
filestats.egg-info/dependency_links.txt
filestats.egg-info/not-zip-safe
filestats.egg-info/top_level.txt