Metadata-Version: 1.0
Name: filestats
Version: 1.2
Summary: Contains functions that return the stats associated with the file 
Home-page: https://github.com/Vutsuak16/filestats
Author: vutsuak
Author-email: vutsuak96@gmail.com
License: MIT
Platform: UNKNOWN
